dstructlib/__init__.py
dstructlib/bst/__init__.py
dstructlib/bst/bst.py
dstructlib/linked_list/__init__.py
dstructlib/linked_list/doubly_linked_list.py
dstructlib/linked_list/singly_linked_list.py
tests/__init__.py
tests/test_bst.py
tests/test_doubly_linked_list.py
tests/test_singly_linked_list.py
dstructslib-1.0.2.dist-info/LICENSE
dstructslib-1.0.2.dist-info/METADATA
dstructslib-1.0.2.dist-info/WHEEL
dstructslib-1.0.2.dist-info/top_level.txt
dstructslib-1.0.2.dist-info/RECORD
